pylibclang-318.1.1.dist-info/METADATA
pylibclang-318.1.1.dist-info/RECORD
pylibclang-318.1.1.dist-info/WHEEL
pylibclang-318.1.1.dist-info/top_level.txt
pylibclang/cindex.py
pylibclang/_C.cpython-312-x86_64-linux-gnu.so
pylibclang/__init__.py
pylibclang/libclang.so.18.1
