Metadata-Version: 2.1
Name: pylibclang
Version: 318.1.1
Summary: A fully featured & always updated python binding for libclang.
License: MIT
Project-URL: Homepage, https://github.com/edimetia3d/pylibclang
Project-URL: Documentation, https://github.com/edimetia3d/pylibclang
Project-URL: Repository, https://github.com/edimetia3d/pylibclang
Project-URL: Changelog, https://github.com/edimetia3d/pylibclang/releases
Keywords: pybind11,libclang,python
Classifier: Development Status :: 4 - Beta
Classifier: Intended Audience :: Developers
Classifier: License :: OSI Approved :: MIT License
Classifier: Programming Language :: Python :: 3
Classifier: Topic :: Software Development :: Compilers
